localsnap.py
localsnap-1.0.0.dist-info/DESCRIPTION.rst
localsnap-1.0.0.dist-info/METADATA
localsnap-1.0.0.dist-info/RECORD
localsnap-1.0.0.dist-info/WHEEL
localsnap-1.0.0.dist-info/entry_points.txt
localsnap-1.0.0.dist-info/metadata.json
localsnap-1.0.0.dist-info/top_level.txt
