Metadata-Version: 2.0
Name: localsnap
Version: 1.0.0
Summary: Offline Snap! runner and manager
Home-page: https://github.com/BookOwl/snap-offline
Author: Matthew
Author-email: Unknown
License: MIT
Keywords: Snap! downloader runner
Platform: UNKNOWN
Classifier: Development Status :: 5 - Production/Stable
Classifier: Intended Audience :: Developers
Classifier: License :: OSI Approved :: MIT License
Classifier: Programming Language :: Python :: 2
Classifier: Programming Language :: Python :: 2.7
Classifier: Programming Language :: Python :: 3
Classifier: Programming Language :: Python :: 3.1
Classifier: Programming Language :: Python :: 3.2
Classifier: Programming Language :: Python :: 3.3
Classifier: Programming Language :: Python :: 3.4
Classifier: Programming Language :: Python :: 3.5
Requires-Dist: requests
